physai/__init__.py
physai/losses.py
physai/pde_residual.py
physai/physics.py
physai/pinn.py
physai/trainer.py
physai/utils.py
physai/visualization.py
physai-3.0.0.dist-info/licenses/LICENSE
physai-3.0.0.dist-info/METADATA
physai-3.0.0.dist-info/WHEEL
physai-3.0.0.dist-info/top_level.txt
physai-3.0.0.dist-info/RECORD
