Metadata-Version: 2.4
Name: physai
Version: 3.0.0
Summary: Physics-Informed Neural Network (PINN) library for solving and animating ODEs/PDEs with visualization and training tools
Author-email: Mankrit Singh <whataninfinity@gmail.com>
License: # Modified Apache License, Version 2.0
Project-URL: homepage, https://github.com/MS-AGI/PhysAI
Project-URL: documentation, https://github.com/MS-AGI/PhysAI
Project-URL: source, https://github.com/MS-AGI/PhysAI
Project-URL: doi, https://doi.org/10.5281/zenodo.17214724
Keywords: PINN,Physics-Informed Neural Network,ODE,PDE,Deep Learning,Modular Library,Built-in PDE support,Efficient and Fast Training for Great PDE Solving and visualization,Built-in Partial Differential Equations using pre-made PINN
Requires-Python: >=3.9
License-File: LICENSE
Requires-Dist: torch>=2.8.0
Requires-Dist: matplotlib
Requires-Dist: numpy
Dynamic: license-file
